psrc/__init__.py
psrc/_modidx.py
psrc/chck.py
psrc/dcom.py
psrc/dsrc.py
psrc/enums.py
psrc/exts.py
psrc/gzip.py
psrc/hrdw.py
psrc/ldir.py
psrc/leaf.py
psrc/pfmt.py
psrc/plib.py
psrc/pttn.py
psrc/srcs.py
psrc/ssrc.py
psrc/urls.py
psrc/user.py
psrc/util.py
psrc/walk.py
psrc-0.0.19.dist-info/LICENSE
psrc-0.0.19.dist-info/METADATA
psrc-0.0.19.dist-info/WHEEL
psrc-0.0.19.dist-info/entry_points.txt
psrc-0.0.19.dist-info/top_level.txt
psrc-0.0.19.dist-info/RECORD
