Metadata-Version: 2.1
Name: psrc
Version: 0.0.19
Summary: structured directories
Home-page: https://github.com/dsm-72/psrc
Author: dsm-72
Author-email: sumner.magruder@yale.edu
License: Apache Software License 2.0
Classifier: Development Status :: 4 - Beta
Classifier: Intended Audience :: Developers
Classifier: Natural Language :: English
Classifier: Programming Language :: Python :: 3.11
Classifier: License :: OSI Approved :: Apache Software License
Requires-Python: >=3.11
License-File: LICENSE
Requires-Dist: quac
Requires-Dist: nchr
Requires-Dist: nlit
Requires-Dist: chck
Requires-Dist: atup
Requires-Dist: asto
Requires-Dist: ispec
Requires-Dist: aspec
Provides-Extra: dev
Requires-Dist: urllib3 ; extra == 'dev'
Requires-Dist: requests ; extra == 'dev'
Requires-Dist: tqdm ; extra == 'dev'
